refact/__init__.py
refact/chat_client.py
refact/cli_app_switcher.py
refact/cli_export.py
refact/cli_inspect.py
refact/cli_main.py
refact/cli_markdown.py
refact/cli_printing.py
refact/cli_settings.py
refact/cli_statusbar.py
refact/cli_streaming.py
refact/lsp_runner.py
refact/traj_compressor.py
refact/bin/refact-lsp
refact-0.10.14.data/data/bin/refact-lsp
refact-0.10.14.dist-info/METADATA
refact-0.10.14.dist-info/WHEEL
refact-0.10.14.dist-info/entry_points.txt
refact-0.10.14.dist-info/top_level.txt
refact-0.10.14.dist-info/RECORD
